contact_user_externals_local/__init__.py
contact_user_externals_local/contact_user_externals_local.py
contact_user_externals_local/contact_user_externals_local_constants.py
contact_user_externals_local-0.0.2.dist-info/METADATA
contact_user_externals_local-0.0.2.dist-info/WHEEL
contact_user_externals_local-0.0.2.dist-info/top_level.txt
contact_user_externals_local-0.0.2.dist-info/RECORD
